Metadata-Version: 2.1
Name: odoo11-addon-mrp-mto-with-stock
Version: 11.0.2.0.1
Summary: Fix Manufacturing orders to pull from stock until qty is zero, and then create a procurement for them.
Home-page: https://odoo-community.org/
Author: John Walsh, Eficent, Odoo Community Association (OCA)
Author-email: support@odoo-community.org
License: AGPL-3
Platform: UNKNOWN
Classifier: Programming Language :: Python
Classifier: Framework :: Odoo
Classifier: License :: OSI Approved :: GNU Affero General Public License v3
Requires-Python: >=2.7, !=3.0.*, !=3.1.*, !=3.2.*, !=3.3.*, !=3.4.*
Requires-Dist: odoo11-addon-stock-available-unreserved
Requires-Dist: odoo (<11.1dev,>=11.0a)
